ssearch/__init__.py
ssearch/ssearch.py
ssearch-0.0.5.dist-info/LICENSE
ssearch-0.0.5.dist-info/METADATA
ssearch-0.0.5.dist-info/WHEEL
ssearch-0.0.5.dist-info/entry_points.txt
ssearch-0.0.5.dist-info/top_level.txt
ssearch-0.0.5.dist-info/RECORD
