Metadata-Version: 2.1
Name: ssearch
Version: 0.0.5
Summary: sougo translate cli tool
Home-page: https://github.com/xyok/ssearch.git
Author: xyok
Author-email: xy___ok@163.com
License: MIT
Keywords: cli,translate,chinese
Platform: UNKNOWN
Classifier: Programming Language :: Python :: 3
Classifier: Programming Language :: Python :: 2.7
Classifier: License :: OSI Approved :: MIT License
Classifier: Operating System :: OS Independent
Requires-Dist: requests
